tests/__init__.py
tests/context.py
tests/test_basic.py
tracer/__init__.py
tracer/main.py
http_tracer-19.7.3.dist-info/LICENCE.txt
http_tracer-19.7.3.dist-info/METADATA
http_tracer-19.7.3.dist-info/WHEEL
http_tracer-19.7.3.dist-info/entry_points.txt
http_tracer-19.7.3.dist-info/top_level.txt
http_tracer-19.7.3.dist-info/RECORD
